MiniMVC/MiniMVC.py
MiniMVC/__init__.py
MiniMVC-0.0.1.dist-info/METADATA
MiniMVC-0.0.1.dist-info/WHEEL
MiniMVC-0.0.1.dist-info/top_level.txt
MiniMVC-0.0.1.dist-info/RECORD
