Metadata-Version: 2.1
Name: MiniMVC
Version: 0.0.1
Summary: MiniMVC is a lightweight, open-source web framework for building small web applications in Python.
Author: Dekel Cohen
Author-email: <dcohen52@gmail.com>
Keywords: python,web,framework,desktop,html,javascript,styles,js,API,microservices,REST
Classifier: Development Status :: 1 - Planning
Classifier: Intended Audience :: Developers
Classifier: Programming Language :: Python :: 3
Classifier: Operating System :: Unix
Classifier: Operating System :: MacOS :: MacOS X
Classifier: Operating System :: Microsoft :: Windows
Requires-Dist: Jinja2
